{
    "path": "data/text/86.txt",
    "token":  {
        "ner": ["人物", "学校", "工作单位"], 
        "information": {
            "人物": ["性别", "出生日期", "年龄", "职务", "电话", "邮箱", "学历"],
            "学校": ["学历", "专业", "时间", "时间段"],
            "工作单位": ["职务", "时间", "时间段"]
        }, 
        "event": {}
    },
    "result": {
        "ner": {
            "人物": ["刘佳雨"],
            "学校": ["陕西工业职业技术学院"],
            "工作单位": ["世程文化发展有限公司", "利亚科技业务部客服中心"]
        },
        "information": {
            "刘佳雨": {
                "性别": [],
                "出生日期": ["1888888888"],
                "年龄": ["30岁"],
                "职务": ["产品设计"],
                "电话": ["1888888888888888"],
                "邮箱": [],
                "学历": []
            },
            "陕西工业职业技术学院": {
                "学历": [],
                "专业": ["工商管理"],
                "时间": ["2011.9", "2014.6"],
                "时间段": ["2011.9-2014.6"]
            },
            "世程文化发展有限公司": {
                "职务": ["市场助理"],
                "时间": ["2017.7", "2022.9"],
                "时间段": ["2017.7-2022.9"]
            },
            "利亚科技业务部客服中心": {
                "职务": ["客服组长"],
                "时间": ["2017.7", "2014.7"],
                "时间段": ["2014.7-2017.7"]
            }
        },
        "event": {}
    }
}